echotorch/__init__.py
echotorch/timetensor.py
echotorch/utility_functions.py
echotorch/datasets/CopyTaskDataset.py
echotorch/datasets/DatasetComposer.py
echotorch/datasets/DiscreteMarkovChainDataset.py
echotorch/datasets/FromCSVDataset.py
echotorch/datasets/HenonAttractor.py
echotorch/datasets/ImageToTimeseries.py
echotorch/datasets/LambdaDataset.py
echotorch/datasets/LatchTaskDataset.py
echotorch/datasets/LogisticMapDataset.py
echotorch/datasets/LorenzAttractor.py
echotorch/datasets/MackeyGlass2DDataset.py
echotorch/datasets/MackeyGlassDataset.py
echotorch/datasets/MarkovChainDataset.py
echotorch/datasets/MemTestDataset.py
echotorch/datasets/MixedSinesDataset.py
echotorch/datasets/NARMADataset.py
echotorch/datasets/PeriodicSignalDataset.py
echotorch/datasets/RandomSymbolDataset.py
echotorch/datasets/RepeatTaskDataset.py
echotorch/datasets/RosslerAttractor.py
echotorch/datasets/SinusoidalTimeseries.py
echotorch/datasets/SwitchAttractorDataset.py
echotorch/datasets/TimeseriesBatchSequencesDataset.py
echotorch/datasets/TransformDataset.py
echotorch/datasets/TripletBatching.py
echotorch/datasets/__init__.py
echotorch/datasetspy2/CopyTaskDataset.py
echotorch/datasetspy2/DatasetComposer.py
echotorch/datasetspy2/DiscreteMarkovChainDataset.py
echotorch/datasetspy2/FromCSVDataset.py
echotorch/datasetspy2/HenonAttractor.py
echotorch/datasetspy2/ImageToTimeseries.py
echotorch/datasetspy2/LambdaDataset.py
echotorch/datasetspy2/LatchTaskDataset.py
echotorch/datasetspy2/LogisticMapDataset.py
echotorch/datasetspy2/LorenzAttractor.py
echotorch/datasetspy2/MackeyGlass2DDataset.py
echotorch/datasetspy2/MackeyGlassDataset.py
echotorch/datasetspy2/MarkovChainDataset.py
echotorch/datasetspy2/MemTestDataset.py
echotorch/datasetspy2/MixedSinesDataset.py
echotorch/datasetspy2/NARMADataset.py
echotorch/datasetspy2/PeriodicSignalDataset.py
echotorch/datasetspy2/RandomSymbolDataset.py
echotorch/datasetspy2/RepeatTaskDataset.py
echotorch/datasetspy2/RosslerAttractor.py
EchoTorch_PyTorch2Build-1.0.0.dist-info/LICENSE
EchoTorch_PyTorch2Build-1.0.0.dist-info/LICENSE.txt
EchoTorch_PyTorch2Build-1.0.0.dist-info/METADATA
EchoTorch_PyTorch2Build-1.0.0.dist-info/WHEEL
EchoTorch_PyTorch2Build-1.0.0.dist-info/top_level.txt
EchoTorch_PyTorch2Build-1.0.0.dist-info/RECORD
